sqlalchemy_state_machine/__init__.py
sqlalchemy_state_machine/state_mixin.py
sqlalchemy_state_machine/version.py
tests/__init__.py
tests/conftest.py
tests/fixtures.py
tests/test_state_maschine.py
sqlalchemy_state_machine-1.11.0.dist-info/LICENSE
sqlalchemy_state_machine-1.11.0.dist-info/METADATA
sqlalchemy_state_machine-1.11.0.dist-info/WHEEL
sqlalchemy_state_machine-1.11.0.dist-info/top_level.txt
sqlalchemy_state_machine-1.11.0.dist-info/RECORD
